django_salestrack-1.0.3.dist-info/licenses/LICENSE
salestrack/__init__.py
salestrack/apps.py
salestrack/urls.py
salestrack/utils.py
salestrack/views.py
salestrack/templates/salestrack/home.html
django_salestrack-1.0.3.dist-info/METADATA
django_salestrack-1.0.3.dist-info/WHEEL
django_salestrack-1.0.3.dist-info/top_level.txt
django_salestrack-1.0.3.dist-info/RECORD
