Metadata-Version: 2.4
Name: django-salestrack
Version: 1.0.3
Summary: A Django app for tracking sales personnel, distributors, and retailers with Google Maps integration
Home-page: https://github.com/sortstring/django-salestrack
Author: Parijat Srivastava
Author-email: Parijat Srivastava <parijat.shrivastava@sortstring.com>
License: MIT License
Project-URL: Homepage, https://github.com/yourusername/django-salestrack
Project-URL: Repository, https://github.com/yourusername/django-salestrack.git
Project-URL: Documentation, https://github.com/yourusername/django-salestrack#readme
Project-URL: Bug Tracker, https://github.com/yourusername/django-salestrack/issues
Keywords: django,sales,tracking,maps,google-maps,distributor,retailer
Classifier: Development Status :: 5 - Production/Stable
Classifier: Intended Audience :: Developers
Classifier: License :: OSI Approved :: MIT License
Classifier: Operating System :: OS Independent
Classifier: Programming Language :: Python :: 3
Classifier: Programming Language :: Python :: 3.8
Classifier: Programming Language :: Python :: 3.9
Classifier: Programming Language :: Python :: 3.10
Classifier: Programming Language :: Python :: 3.11
Classifier: Framework :: Django
Classifier: Framework :: Django :: 3.2
Classifier: Framework :: Django :: 4.0
Classifier: Framework :: Django :: 4.1
Classifier: Framework :: Django :: 4.2
Classifier: Topic :: Software Development :: Libraries :: Python Modules
Classifier: Topic :: Internet :: WWW/HTTP :: Dynamic Content
Requires-Python: >=3.8
License-File: LICENSE
Requires-Dist: Django>=3.2
Requires-Dist: requests>=2.20.0
Requires-Dist: python-dateutil>=2.7.0
Provides-Extra: mysql
Requires-Dist: mysqlclient>=2.0.0; extra == "mysql"
Requires-Dist: django-mysql>=4.5.0; extra == "mysql"
Provides-Extra: api
Requires-Dist: djangorestframework>=3.13.0; extra == "api"
Provides-Extra: dev
Requires-Dist: pytest>=6.0; extra == "dev"
Requires-Dist: pytest-django>=4.0; extra == "dev"
Requires-Dist: coverage>=5.0; extra == "dev"
Requires-Dist: black>=21.0; extra == "dev"
Requires-Dist: flake8>=3.8; extra == "dev"
Dynamic: author
Dynamic: home-page
Dynamic: license-file
Dynamic: requires-python
